livehttp/__init__.py
livehttp/__main__.py
livehttp/livehttp.py
livehttp/logx/__init__.py
livehttp/logx/colored_handler.py
livehttp/logx/logging.yaml
livehttp/logx/setup_logging.py
livehttp/templates/files.html
livehttp/templates/index.html
livehttp-0.0.7.dist-info/METADATA
livehttp-0.0.7.dist-info/WHEEL
livehttp-0.0.7.dist-info/entry_points.txt
livehttp-0.0.7.dist-info/top_level.txt
livehttp-0.0.7.dist-info/RECORD
